pyremoteview/__init__.py
pyremoteview/remote_gallery.py
pyremoteview/templates/gallery.html
pyremoteview-1.0.2.dist-info/licenses/LICENSE
pyremoteview-1.0.2.dist-info/METADATA
pyremoteview-1.0.2.dist-info/WHEEL
pyremoteview-1.0.2.dist-info/entry_points.txt
pyremoteview-1.0.2.dist-info/top_level.txt
pyremoteview-1.0.2.dist-info/RECORD
