Metadata-Version: 2.4
Name: pyremoteview
Version: 1.0.2
Summary: Remote SSH or Local Image Gallery Viewer
Home-page: https://github.com/alesaccoia/pyremoteview
Author: Alessandro Saccoia
Author-email: alessandro.saccoia@gmail.com
License: MIT
Keywords: ssh remote image gallery viewer thumbnail
Classifier: Development Status :: 3 - Alpha
Classifier: Environment :: Web Environment
Classifier: Intended Audience :: End Users/Desktop
Classifier: License :: OSI Approved :: MIT License
Classifier: Operating System :: POSIX :: Linux
Classifier: Programming Language :: Python :: 3
Classifier: Programming Language :: Python :: 3.6
Classifier: Programming Language :: Python :: 3.7
Classifier: Programming Language :: Python :: 3.8
Classifier: Programming Language :: Python :: 3.9
Classifier: Programming Language :: Python :: 3.10
Classifier: Topic :: Multimedia :: Graphics :: Viewers
Classifier: Topic :: Internet :: WWW/HTTP :: Dynamic Content
Requires-Python: >=3.6
License-File: LICENSE
Requires-Dist: flask>=2.0.0
Requires-Dist: pillow>=8.0.0
Requires-Dist: werkzeug>=2.0.0
Dynamic: author
Dynamic: author-email
Dynamic: classifier
Dynamic: description
Dynamic: description-content-type
Dynamic: home-page
Dynamic: keywords
Dynamic: license
Dynamic: license-file
Dynamic: requires-dist
Dynamic: requires-python
Dynamic: summary
